# 23 Nexus Opener
Build order taken from replay "PvT - 23 Nex Open.rep" by dB)Teame.

## Core Setup
- 8/9 Pylon
- 10/17 Gate
- 11/17 Assimilator
- 12/17 Core
- 15/17 Pylon
  - 15/17 Send Pylon-building Probe out to Scout
- 17/25 Goon (use as scout, check for CC)
- 20/25 Goon Range
- 21/25 Goon
  - Stop Building Probes
- 23/25 Nexus
- 23/25 Pylon

## Scouting Intel
- 23/25 Scouting with 1st Goon, CC found?
  - yes: 2x Probe
  - no:  Goon

## Core Setup
- 25/33 Robo
- Resume Building Probes
- 26/33 Goon
- 29/33 Gate
- 30/33 Goon
- Stop Building Probes
- Nexus finishes, increasing max. supply to 42
- 32/42 Observatory
- 32/42 Gate
- 32/42 Pylon
- 32/42 Goon
- 34/42 Goon
- Resume Building Probes
- 38/42 Observer
- 41/50 Pylon
- 43/50 Goon
- 45/50 Goon
- 47/50 Goon
- 51/58 Pylon
- Good Luck!

## Mission Objectives From Here On
- Clear the way to the third (VultureMinesweeping)
- Get Map Control (Minesweeping)
- Get 3rd Nexus

## Benchmarks at 6:00 Minutes:
- 30 Probes
- 6  Goons
- 1  Observer
